shellody/__init__.py
shellody/arguments.py
shellody/completion.py
shellody/shell.py
shellody-0.14.dist-info/METADATA
shellody-0.14.dist-info/WHEEL
shellody-0.14.dist-info/RECORD
